mobilepass
