Metadata-Version: 1.2
Name: MobilePASS
Version: 2.1.1
Summary: Generate OTP based on activation key from SafeNet MobilePASS
Home-page: https://github.com/rantanevich/MobilePASSER
Maintainer: Raman Antanevich
Maintainer-email: r.antanevich@ya.ru
License: UNKNOWN
Platform: UNKNOWN
